sane_logger/__init__.py
sane_logger/sane_logger.py
sane_logger-0.0.6.dist-info/LICENSE
sane_logger-0.0.6.dist-info/METADATA
sane_logger-0.0.6.dist-info/WHEEL
sane_logger-0.0.6.dist-info/top_level.txt
sane_logger-0.0.6.dist-info/zip-safe
sane_logger-0.0.6.dist-info/RECORD
