Metadata-Version: 2.1
Name: sane-logger
Version: 0.0.6
Summary: My preferred logger config.
Home-page: https://github.com/JesseAldridge/sane_logger
Author: Jesse Aldridge
Author-email: JesseAldridge@gmail.com
License: MIT
Keywords: logging
License-File: LICENSE
